avidtools/__init__.py
avidtools/connectors/__init__.py
avidtools/connectors/aiid.py
avidtools/connectors/atlas.py
avidtools/connectors/cve.py
avidtools/connectors/inspect.py
avidtools/datamodels/__init__.py
avidtools/datamodels/components.py
avidtools/datamodels/enums.py
avidtools/datamodels/report.py
avidtools/datamodels/vulnerability.py
avidtools-0.2.1.dist-info/LICENSE
avidtools-0.2.1.dist-info/METADATA
avidtools-0.2.1.dist-info/WHEEL
avidtools-0.2.1.dist-info/RECORD
