Metadata-Version: 2.3
Name: avidtools
Version: 0.2.1
Summary: Developer tools for AVID
License: Apache-2.0
Keywords: ai,vulnerability,security,machine-learning,avid
Author: Subho Majumdar
Author-email: subho@avidml.org
Requires-Python: >=3.12
Classifier: Development Status :: 4 - Beta
Classifier: Intended Audience :: Developers
Classifier: License :: OSI Approved :: Apache Software License
Classifier: Programming Language :: Python :: 3.12
Classifier: Topic :: Security
Classifier: Topic :: Software Development :: Libraries :: Python Modules
Requires-Dist: nvdlib (>=0.8.1,<0.9.0)
Requires-Dist: pydantic (>=2.11.5,<3.0.0)
Requires-Dist: typing-extensions (>=4.13.2,<5.0.0)
Project-URL: Bug Tracker, https://github.com/avidml/avidtools/issues
Project-URL: Documentation, https://github.com/avidml/avidtools
Project-URL: Homepage, https://github.com/avidml/avidtools
Project-URL: Repository, https://github.com/avidml/avidtools
